{
	"fetched": 49,
	"records": [
		{
			"attributes": {
				"type": "PSR_Operation_Date__c",
				"url": "/services/data/v51.0/sobjects/PSR_Operation_Date__c/a1wJ0000004FQQqIAO"
			},
			"Id": "a1wJ0000004FQQqIAO",
			"Name": "ABSP",
			"Operation__c": "a0X1I000002pqt0UAA",
			"PSR_Date__c": null,
			"PSR_Event_Name__c": "Abstract Presentation"
		},
		{
			"attributes": {
				"type": "PSR_Operation_Date__c",
				"url": "/services/data/v51.0/sobjects/PSR_Operation_Date__c/a1wJ0000004FQQrIAO"
			},
			"Id": "a1wJ0000004FQQrIAO",
			"Name": "DCM",
			"Operation__c": "a0X1I000002pqt0UAA",
			"PSR_Date__c": "2017-03-22",
			"PSR_Event_Name__c": "Donors Committee"
		},
		{
			"attributes": {
				"type": "PSR_Operation_Date__c",
				"url": "/services/data/v51.0/sobjects/PSR_Operation_Date__c/a1wJ0000004FQQsIAO"
			},
			"Id": "a1wJ0000004FQQsIAO",
			"Name": "RAT",
			"Operation__c": "a0X1I000002pqt0UAA",
			"PSR_Date__c": null,
			"PSR_Event_Name__c": "Ratification"
		},
		{
			"attributes": {
				"type": "PSR_Operation_Date__c",
				"url": "/services/data/v51.0/sobjects/PSR_Operation_Date__c/a1wJ0000004FQQtIAO"
			},
			"Id": "a1wJ0000004FQQtIAO",
			"Name": "CO",
			"Operation__c": "a0X1I000002pqt0UAA",
			"PSR_Date__c": null,
			"PSR_Event_Name__c": "Fully Justified"
		},
		{
			"attributes": {
				"type": "PSR_Operation_Date__c",
				"url": "/services/data/v51.0/sobjects/PSR_Operation_Date__c/a1wJ0000004FQQuIAO"
			},
			"Id": "a1wJ0000004FQQuIAO",
			"Name": "QRR",
			"Operation__c": "a0X1I000002pqt0UAA",
			"PSR_Date__c": null,
			"PSR_Event_Name__c": "POD Distribution to QRR"
		},
		{
			"attributes": {
				"type": "PSR_Operation_Date__c",
				"url": "/services/data/v51.0/sobjects/PSR_Operation_Date__c/a1wJ0000004FQQvIAO"
			},
			"Id": "a1wJ0000004FQQvIAO",
			"Name": "CED",
			"Operation__c": "a0X1I000002pqt0UAA",
			"PSR_Date__c": "2021-09-22",
			"PSR_Event_Name__c": "Current Last Disbursement Expiration Date"
		},
		{
			"attributes": {
				"type": "PSR_Operation_Date__c",
				"url": "/services/data/v51.0/sobjects/PSR_Operation_Date__c/a1wJ0000004FQQwIAO"
			},
			"Id": "a1wJ0000004FQQwIAO",
			"Name": "TEL",
			"Operation__c": "a0X1I000002pqt0UAA",
			"PSR_Date__c": "2018-03-27",
			"PSR_Event_Name__c": "Total Eligibility"
		},
		{
			"attributes": {
				"type": "PSR_Operation_Date__c",
				"url": "/services/data/v51.0/sobjects/PSR_Operation_Date__c/a1wJ0000004FQQxIAO"
			},
			"Id": "a1wJ0000004FQQxIAO",
			"Name": "ON",
			"Operation__c": "a0X1I000002pqt0UAA",
			"PSR_Date__c": "2017-03-27",
			"PSR_Event_Name__c": "Activate/ Registration"
		},
		{
			"attributes": {
				"type": "PSR_Operation_Date__c",
				"url": "/services/data/v51.0/sobjects/PSR_Operation_Date__c/a1wJ0000004FQQyIAO"
			},
			"Id": "a1wJ0000004FQQyIAO",
			"Name": "ESS",
			"Operation__c": "a0X1I000002pqt0UAA",
			"PSR_Date__c": null,
			"PSR_Event_Name__c": "CESI - Environmental and Social Strategy"
		},
		{
			"attributes": {
				"type": "PSR_Operation_Date__c",
				"url": "/services/data/v51.0/sobjects/PSR_Operation_Date__c/a1wJ0000004FQQzIAO"
			},
			"Id": "a1wJ0000004FQQzIAO",
			"Name": "SECC",
			"Operation__c": "a0X1I000002pqt0UAA",
			"PSR_Date__c": null,
			"PSR_Event_Name__c": "SEC - Changes post Negotiation"
		},
		{
			"attributes": {
				"type": "PSR_Operation_Date__c",
				"url": "/services/data/v51.0/sobjects/PSR_Operation_Date__c/a1wJ0000004FQR0IAO"
			},
			"Id": "a1wJ0000004FQR0IAO",
			"Name": "DI",
			"Operation__c": "a0X1I000002pqt0UAA",
			"PSR_Date__c": "2018-03-29",
			"PSR_Event_Name__c": "Disbursing"
		},
		{
			"attributes": {
				"type": "PSR_Operation_Date__c",
				"url": "/services/data/v51.0/sobjects/PSR_Operation_Date__c/a1wJ0000004FQR1IAO"
			},
			"Id": "a1wJ0000004FQR1IAO",
			"Name": "KICK",
			"Operation__c": "a0X1I000002pqt0UAA",
			"PSR_Date__c": null,
			"PSR_Event_Name__c": "Kick-Off Meeting"
		},
		{
			"attributes": {
				"type": "PSR_Operation_Date__c",
				"url": "/services/data/v51.0/sobjects/PSR_Operation_Date__c/a1wJ0000004FQR2IAO"
			},
			"Id": "a1wJ0000004FQR2IAO",
			"Name": "FD",
			"Operation__c": "a0X1I000002pqt0UAA",
			"PSR_Date__c": null,
			"PSR_Event_Name__c": "Fully Disbursed"
		},
		{
			"attributes": {
				"type": "PSR_Operation_Date__c",
				"url": "/services/data/v51.0/sobjects/PSR_Operation_Date__c/a1wJ0000004FQR3IAO"
			},
			"Id": "a1wJ0000004FQR3IAO",
			"Name": "EOC",
			"Operation__c": "a0X1I000002pqt0UAA",
			"PSR_Date__c": "2021-12-21",
			"PSR_Event_Name__c": "Estimated Operational Close"
		},
		{
			"attributes": {
				"type": "PSR_Operation_Date__c",
				"url": "/services/data/v51.0/sobjects/PSR_Operation_Date__c/a1wJ0000004FQR4IAO"
			},
			"Id": "a1wJ0000004FQR4IAO",
			"Name": "APPR",
			"Operation__c": "a0X1I000002pqt0UAA",
			"PSR_Date__c": "2017-03-22",
			"PSR_Event_Name__c": "Approval Date"
		},
		{
			"attributes": {
				"type": "PSR_Operation_Date__c",
				"url": "/services/data/v51.0/sobjects/PSR_Operation_Date__c/a1wJ0000004FQR5IAO"
			},
			"Id": "a1wJ0000004FQR5IAO",
			"Name": "95D",
			"Operation__c": "a0X1I000002pqt0UAA",
			"PSR_Date__c": null,
			"PSR_Event_Name__c": "After 95% Disbursed"
		},
		{
			"attributes": {
				"type": "PSR_Operation_Date__c",
				"url": "/services/data/v51.0/sobjects/PSR_Operation_Date__c/a1wJ0000004FQR6IAO"
			},
			"Id": "a1wJ0000004FQR6IAO",
			"Name": "MIFE",
			"Operation__c": "a0X1I000002pqt0UAA",
			"PSR_Date__c": null,
			"PSR_Event_Name__c": "MIF/Fund Eligible"
		},
		{
			"attributes": {
				"type": "PSR_Operation_Date__c",
				"url": "/services/data/v51.0/sobjects/PSR_Operation_Date__c/a1wJ0000004FQR7IAO"
			},
			"Id": "a1wJ0000004FQR7IAO",
			"Name": "OED",
			"Operation__c": "a0X1I000002pqt0UAA",
			"PSR_Date__c": "2020-09-22",
			"PSR_Event_Name__c": "Original Last Disbursement Expiration Date"
		},
		{
			"attributes": {
				"type": "PSR_Operation_Date__c",
				"url": "/services/data/v51.0/sobjects/PSR_Operation_Date__c/a1wJ0000004FQR8IAO"
			},
			"Id": "a1wJ0000004FQR8IAO",
			"Name": "COO",
			"Operation__c": "a0X1I000002pqt0UAA",
			"PSR_Date__c": null,
			"PSR_Event_Name__c": "Operative Close"
		},
		{
			"attributes": {
				"type": "PSR_Operation_Date__c",
				"url": "/services/data/v51.0/sobjects/PSR_Operation_Date__c/a1wJ0000004FQR9IAO"
			},
			"Id": "a1wJ0000004FQR9IAO",
			"Name": "SI",
			"Operation__c": "a0X1I000002pqt0UAA",
			"PSR_Date__c": "2017-09-22",
			"PSR_Event_Name__c": "Signature Date"
		},
		{
			"attributes": {
				"type": "PSR_Operation_Date__c",
				"url": "/services/data/v51.0/sobjects/PSR_Operation_Date__c/a1wJ0000004FQRAIA4"
			},
			"Id": "a1wJ0000004FQRAIA4",
			"Name": "CF",
			"Operation__c": "a0X1I000002pqt0UAA",
			"PSR_Date__c": null,
			"PSR_Event_Name__c": "Financial Close"
		},
		{
			"attributes": {
				"type": "PSR_Operation_Date__c",
				"url": "/services/data/v51.0/sobjects/PSR_Operation_Date__c/a1wJ0000004FQRBIA4"
			},
			"Id": "a1wJ0000004FQRBIA4",
			"Name": "EF",
			"Operation__c": "a0X1I000002pqt0UAA",
			"PSR_Date__c": "2017-09-22",
			"PSR_Event_Name__c": "Effective"
		},
		{
			"attributes": {
				"type": "PSR_Operation_Date__c",
				"url": "/services/data/v51.0/sobjects/PSR_Operation_Date__c/a1wJ0000004FQRCIA4"
			},
			"Id": "a1wJ0000004FQRCIA4",
			"Name": "EVP",
			"Operation__c": "a0X1I000002pqt0UAA",
			"PSR_Date__c": null,
			"PSR_Event_Name__c": "Executive Vice President's revision"
		},
		{
			"attributes": {
				"type": "PSR_Operation_Date__c",
				"url": "/services/data/v51.0/sobjects/PSR_Operation_Date__c/a1wJ0000004FQRDIA4"
			},
			"Id": "a1wJ0000004FQRDIA4",
			"Name": "EL",
			"Operation__c": "a0X1I000002pqt0UAA",
			"PSR_Date__c": "2018-03-27",
			"PSR_Event_Name__c": "First Eligibility"
		},
		{
			"attributes": {
				"type": "PSR_Operation_Date__c",
				"url": "/services/data/v51.0/sobjects/PSR_Operation_Date__c/a1wJ0000004FRbzIAG"
			},
			"Id": "a1wJ0000004FRbzIAG",
			"Name": "CED",
			"Operation__c": "a0X1I000002prNCUAY",
			"PSR_Date__c": "2021-10-19",
			"PSR_Event_Name__c": "Current Last Disbursement Expiration Date"
		},
		{
			"attributes": {
				"type": "PSR_Operation_Date__c",
				"url": "/services/data/v51.0/sobjects/PSR_Operation_Date__c/a1wJ0000004FRc0IAG"
			},
			"Id": "a1wJ0000004FRc0IAG",
			"Name": "EOC",
			"Operation__c": "a0X1I000002prNCUAY",
			"PSR_Date__c": "2022-01-17",
			"PSR_Event_Name__c": "Estimated Operational Close"
		},
		{
			"attributes": {
				"type": "PSR_Operation_Date__c",
				"url": "/services/data/v51.0/sobjects/PSR_Operation_Date__c/a1wJ0000004FRc1IAG"
			},
			"Id": "a1wJ0000004FRc1IAG",
			"Name": "CO",
			"Operation__c": "a0X1I000002prNCUAY",
			"PSR_Date__c": null,
			"PSR_Event_Name__c": "Fully Justified"
		},
		{
			"attributes": {
				"type": "PSR_Operation_Date__c",
				"url": "/services/data/v51.0/sobjects/PSR_Operation_Date__c/a1wJ0000004FRc2IAG"
			},
			"Id": "a1wJ0000004FRc2IAG",
			"Name": "COO",
			"Operation__c": "a0X1I000002prNCUAY",
			"PSR_Date__c": null,
			"PSR_Event_Name__c": "Operative Close"
		},
		{
			"attributes": {
				"type": "PSR_Operation_Date__c",
				"url": "/services/data/v51.0/sobjects/PSR_Operation_Date__c/a1wJ0000004FRc3IAG"
			},
			"Id": "a1wJ0000004FRc3IAG",
			"Name": "FD",
			"Operation__c": "a0X1I000002prNCUAY",
			"PSR_Date__c": null,
			"PSR_Event_Name__c": "Fully Disbursed"
		},
		{
			"attributes": {
				"type": "PSR_Operation_Date__c",
				"url": "/services/data/v51.0/sobjects/PSR_Operation_Date__c/a1wJ0000004FRc4IAG"
			},
			"Id": "a1wJ0000004FRc4IAG",
			"Name": "RAT",
			"Operation__c": "a0X1I000002prNCUAY",
			"PSR_Date__c": null,
			"PSR_Event_Name__c": "Ratification"
		},
		{
			"attributes": {
				"type": "PSR_Operation_Date__c",
				"url": "/services/data/v51.0/sobjects/PSR_Operation_Date__c/a1wJ0000004FRc5IAG"
			},
			"Id": "a1wJ0000004FRc5IAG",
			"Name": "ESS",
			"Operation__c": "a0X1I000002prNCUAY",
			"PSR_Date__c": "2016-11-04",
			"PSR_Event_Name__c": "CESI - Environmental and Social Strategy"
		},
		{
			"attributes": {
				"type": "PSR_Operation_Date__c",
				"url": "/services/data/v51.0/sobjects/PSR_Operation_Date__c/a1wJ0000004FRc6IAG"
			},
			"Id": "a1wJ0000004FRc6IAG",
			"Name": "SI",
			"Operation__c": "a0X1I000002prNCUAY",
			"PSR_Date__c": "2017-04-19",
			"PSR_Event_Name__c": "Signature Date"
		},
		{
			"attributes": {
				"type": "PSR_Operation_Date__c",
				"url": "/services/data/v51.0/sobjects/PSR_Operation_Date__c/a1wJ0000004FRc7IAG"
			},
			"Id": "a1wJ0000004FRc7IAG",
			"Name": "QRR",
			"Operation__c": "a0X1I000002prNCUAY",
			"PSR_Date__c": "2016-11-08",
			"PSR_Event_Name__c": "POD Distribution to QRR"
		},
		{
			"attributes": {
				"type": "PSR_Operation_Date__c",
				"url": "/services/data/v51.0/sobjects/PSR_Operation_Date__c/a1wJ0000004FRc8IAG"
			},
			"Id": "a1wJ0000004FRc8IAG",
			"Name": "ABSP",
			"Operation__c": "a0X1I000002prNCUAY",
			"PSR_Date__c": "2016-06-24",
			"PSR_Event_Name__c": "Abstract Presentation"
		},
		{
			"attributes": {
				"type": "PSR_Operation_Date__c",
				"url": "/services/data/v51.0/sobjects/PSR_Operation_Date__c/a1wJ0000004FRc9IAG"
			},
			"Id": "a1wJ0000004FRc9IAG",
			"Name": "OED",
			"Operation__c": "a0X1I000002prNCUAY",
			"PSR_Date__c": "2020-10-19",
			"PSR_Event_Name__c": "Original Last Disbursement Expiration Date"
		},
		{
			"attributes": {
				"type": "PSR_Operation_Date__c",
				"url": "/services/data/v51.0/sobjects/PSR_Operation_Date__c/a1wJ0000004FRcAIAW"
			},
			"Id": "a1wJ0000004FRcAIAW",
			"Name": "EVP",
			"Operation__c": "a0X1I000002prNCUAY",
			"PSR_Date__c": "2016-11-16",
			"PSR_Event_Name__c": "Executive Vice President's revision"
		},
		{
			"attributes": {
				"type": "PSR_Operation_Date__c",
				"url": "/services/data/v51.0/sobjects/PSR_Operation_Date__c/a1wJ0000004FRcBIAW"
			},
			"Id": "a1wJ0000004FRcBIAW",
			"Name": "ON",
			"Operation__c": "a0X1I000002prNCUAY",
			"PSR_Date__c": "2016-11-03",
			"PSR_Event_Name__c": "Activate/ Registration"
		},
		{
			"attributes": {
				"type": "PSR_Operation_Date__c",
				"url": "/services/data/v51.0/sobjects/PSR_Operation_Date__c/a1wJ0000004FRcCIAW"
			},
			"Id": "a1wJ0000004FRcCIAW",
			"Name": "EF",
			"Operation__c": "a0X1I000002prNCUAY",
			"PSR_Date__c": "2017-04-19",
			"PSR_Event_Name__c": "Effective"
		},
		{
			"attributes": {
				"type": "PSR_Operation_Date__c",
				"url": "/services/data/v51.0/sobjects/PSR_Operation_Date__c/a1wJ0000004FRcDIAW"
			},
			"Id": "a1wJ0000004FRcDIAW",
			"Name": "SECC",
			"Operation__c": "a0X1I000002prNCUAY",
			"PSR_Date__c": null,
			"PSR_Event_Name__c": "SEC - Changes post Negotiation"
		},
		{
			"attributes": {
				"type": "PSR_Operation_Date__c",
				"url": "/services/data/v51.0/sobjects/PSR_Operation_Date__c/a1wJ0000004FRcEIAW"
			},
			"Id": "a1wJ0000004FRcEIAW",
			"Name": "DCM",
			"Operation__c": "a0X1I000002prNCUAY",
			"PSR_Date__c": null,
			"PSR_Event_Name__c": "Donors Committee"
		},
		{
			"attributes": {
				"type": "PSR_Operation_Date__c",
				"url": "/services/data/v51.0/sobjects/PSR_Operation_Date__c/a1wJ0000004FRcFIAW"
			},
			"Id": "a1wJ0000004FRcFIAW",
			"Name": "TCMFR",
			"Operation__c": "a0X1I000002prNCUAY",
			"PSR_Date__c": null,
			"PSR_Event_Name__c": "TCM Final Report Approved"
		},
		{
			"attributes": {
				"type": "PSR_Operation_Date__c",
				"url": "/services/data/v51.0/sobjects/PSR_Operation_Date__c/a1wJ0000004FRcGIAW"
			},
			"Id": "a1wJ0000004FRcGIAW",
			"Name": "EL",
			"Operation__c": "a0X1I000002prNCUAY",
			"PSR_Date__c": "2017-07-07",
			"PSR_Event_Name__c": "First Eligibility"
		},
		{
			"attributes": {
				"type": "PSR_Operation_Date__c",
				"url": "/services/data/v51.0/sobjects/PSR_Operation_Date__c/a1wJ0000004FRcHIAW"
			},
			"Id": "a1wJ0000004FRcHIAW",
			"Name": "DI",
			"Operation__c": "a0X1I000002prNCUAY",
			"PSR_Date__c": "2017-07-20",
			"PSR_Event_Name__c": "Disbursing"
		},
		{
			"attributes": {
				"type": "PSR_Operation_Date__c",
				"url": "/services/data/v51.0/sobjects/PSR_Operation_Date__c/a1wJ0000004FRcIIAW"
			},
			"Id": "a1wJ0000004FRcIIAW",
			"Name": "KICK",
			"Operation__c": "a0X1I000002prNCUAY",
			"PSR_Date__c": null,
			"PSR_Event_Name__c": "Kick-Off Meeting"
		},
		{
			"attributes": {
				"type": "PSR_Operation_Date__c",
				"url": "/services/data/v51.0/sobjects/PSR_Operation_Date__c/a1wJ0000004FRcJIAW"
			},
			"Id": "a1wJ0000004FRcJIAW",
			"Name": "CF",
			"Operation__c": "a0X1I000002prNCUAY",
			"PSR_Date__c": null,
			"PSR_Event_Name__c": "Financial Close"
		},
		{
			"attributes": {
				"type": "PSR_Operation_Date__c",
				"url": "/services/data/v51.0/sobjects/PSR_Operation_Date__c/a1wJ0000004FRcKIAW"
			},
			"Id": "a1wJ0000004FRcKIAW",
			"Name": "95D",
			"Operation__c": "a0X1I000002prNCUAY",
			"PSR_Date__c": null,
			"PSR_Event_Name__c": "After 95% Disbursed"
		},
		{
			"attributes": {
				"type": "PSR_Operation_Date__c",
				"url": "/services/data/v51.0/sobjects/PSR_Operation_Date__c/a1wJ0000004FRcLIAW"
			},
			"Id": "a1wJ0000004FRcLIAW",
			"Name": "MIFE",
			"Operation__c": "a0X1I000002prNCUAY",
			"PSR_Date__c": "2016-06-24",
			"PSR_Event_Name__c": "MIF/Fund Eligible"
		},
		{
			"attributes": {
				"type": "PSR_Operation_Date__c",
				"url": "/services/data/v51.0/sobjects/PSR_Operation_Date__c/a1wJ0000004FRcMIAW"
			},
			"Id": "a1wJ0000004FRcMIAW",
			"Name": "TEL",
			"Operation__c": "a0X1I000002prNCUAY",
			"PSR_Date__c": "2017-07-07",
			"PSR_Event_Name__c": "Total Eligibility"
		},
		{
			"attributes": {
				"type": "PSR_Operation_Date__c",
				"url": "/services/data/v51.0/sobjects/PSR_Operation_Date__c/a1wJ0000004FRcNIAW"
			},
			"Id": "a1wJ0000004FRcNIAW",
			"Name": "APPR",
			"Operation__c": "a0X1I000002prNCUAY",
			"PSR_Date__c": "2016-12-06",
			"PSR_Event_Name__c": "Approval Date"
		}
	],
	"total": 49
}